hello_world/__init__.py
hello_world/_nbdev.py
hello_world/core.py
helloworldToby-0.0.2.dist-info/LICENSE
helloworldToby-0.0.2.dist-info/METADATA
helloworldToby-0.0.2.dist-info/WHEEL
helloworldToby-0.0.2.dist-info/entry_points.txt
helloworldToby-0.0.2.dist-info/top_level.txt
helloworldToby-0.0.2.dist-info/RECORD
