Metadata-Version: 2.1
Name: helloworldToby
Version: 0.0.2
Summary: A small hello world tutorial for nbdev
Home-page: https://github.com/TobyPickard/helloworldToby/tree/master/
Author: Toby
Author-email: pretend@email.com
License: Apache Software License 2.0
Keywords: some keywords
Platform: UNKNOWN
Classifier: Development Status :: 3 - Alpha
Classifier: Intended Audience :: Developers
Classifier: Natural Language :: English
Classifier: Programming Language :: Python :: 3.6
Classifier: Programming Language :: Python :: 3.7
Classifier: Programming Language :: Python :: 3.8
Classifier: License :: OSI Approved :: Apache Software License
Requires-Python: >=3.6
License-File: LICENSE
Requires-Dist: pip
Requires-Dist: packaging
Provides-Extra: dev
